{"total_count":3,"jobs":[{"id":4549025388,"run_id":1588015656,"run_url":"https://api.github.com/repos/dhis2/dhis2-core/actions/runs/1588015656","run_attempt":1,"node_id":"CR_kwDOA_1uaM8AAAABDySebA","head_sha":"e7cbf474d4f163296e1ee60e5e25f54a05fdf0ff","url":"https://api.github.com/repos/dhis2/dhis2-core/actions/jobs/4549025388","html_url":"https://github.com/dhis2/dhis2-core/runs/4549025388?check_suite_focus=true","status":"completed","conclusion":"success","started_at":"2021-12-16T14:51:35Z","completed_at":"2021-12-16T14:51:43Z","name":"cleanup-runs","steps":[{"name":"Set up job","status":"completed","conclusion":"success","number":1,"started_at":"2021-12-16T14:51:35.000Z","completed_at":"2021-12-16T14:51:37.000Z"},{"name":"Build rokroskar/workflow-run-cleanup-action@035a48f84b47e111d72cf492a513179c92cd29ed","status":"completed","conclusion":"success","number":2,"started_at":"2021-12-16T14:51:37.000Z","completed_at":"2021-12-16T14:51:42.000Z"},{"name":"Run rokroskar/workflow-run-cleanup-action@035a48f84b47e111d72cf492a513179c92cd29ed","status":"completed","conclusion":"success","number":3,"started_at":"2021-12-16T14:51:42.000Z","completed_at":"2021-12-16T14:51:43.000Z"},{"name":"Complete job","status":"completed","conclusion":"success","number":4,"started_at":"2021-12-16T14:51:43.000Z","completed_at":"2021-12-16T14:51:43.000Z"}],"check_run_url":"https://api.github.com/repos/dhis2/dhis2-core/check-runs/4549025388","labels":["ubuntu-latest"],"runner_id":4,"runner_name":"GitHub Actions 4","runner_group_id":2,"runner_group_name":"GitHub Actions"},{"id":4549025599,"run_id":1588015656,"run_url":"https://api.github.com/repos/dhis2/dhis2-core/actions/runs/1588015656","run_attempt":1,"node_id":"CR_kwDOA_1uaM8AAAABDySfPw","head_sha":"e7cbf474d4f163296e1ee60e5e25f54a05fdf0ff","url":"https://api.github.com/repos/dhis2/dhis2-core/actions/jobs/4549025599","html_url":"https://github.com/dhis2/dhis2-core/runs/4549025599?check_suite_focus=true","status":"completed","conclusion":"failure","started_at":"2021-12-16T14:51:34Z","completed_at":"2021-12-16T15:00:28Z","name":"integration-test","steps":[{"name":"Set up job","status":"completed","conclusion":"success","number":1,"started_at":"2021-12-16T14:51:34.000Z","completed_at":"2021-12-16T14:51:36.000Z"},{"name":"Run actions/checkout@v1","status":"completed","conclusion":"success","number":2,"started_at":"2021-12-16T14:51:36.000Z","completed_at":"2021-12-16T14:51:50.000Z"},{"name":"Set up JDK 1.8","status":"completed","conclusion":"success","number":3,"started_at":"2021-12-16T14:51:50.000Z","completed_at":"2021-12-16T14:51:54.000Z"},{"name":"Run actions/cache@v1","status":"completed","conclusion":"success","number":4,"started_at":"2021-12-16T14:51:54.000Z","completed_at":"2021-12-16T14:51:55.000Z"},{"name":"Run integration tests","status":"completed","conclusion":"failure","number":5,"started_at":"2021-12-16T14:51:55.000Z","completed_at":"2021-12-16T15:00:28.000Z"},{"name":"Post Run actions/cache@v1","status":"completed","conclusion":"skipped","number":9,"started_at":"2021-12-16T15:00:28.000Z","completed_at":"2021-12-16T15:00:28.000Z"},{"name":"Post Set up JDK 1.8","status":"completed","conclusion":"success","number":10,"started_at":"2021-12-16T15:00:28.000Z","completed_at":"2021-12-16T15:00:28.000Z"},{"name":"Complete job","status":"completed","conclusion":"success","number":11,"started_at":"2021-12-16T15:00:28.000Z","completed_at":"2021-12-16T15:00:28.000Z"}],"check_run_url":"https://api.github.com/repos/dhis2/dhis2-core/check-runs/4549025599","labels":["ubuntu-latest"],"runner_id":5,"runner_name":"GitHub Actions 5","runner_group_id":2,"runner_group_name":"GitHub Actions"},{"id":4549025826,"run_id":1588015656,"run_url":"https://api.github.com/repos/dhis2/dhis2-core/actions/runs/1588015656","run_attempt":1,"node_id":"CR_kwDOA_1uaM8AAAABDySgIg","head_sha":"e7cbf474d4f163296e1ee60e5e25f54a05fdf0ff","url":"https://api.github.com/repos/dhis2/dhis2-core/actions/jobs/4549025826","html_url":"https://github.com/dhis2/dhis2-core/runs/4549025826?check_suite_focus=true","status":"completed","conclusion":"failure","started_at":"2021-12-16T14:51:34Z","completed_at":"2021-12-16T14:59:32Z","name":"unit-test","steps":[{"name":"Set up job","status":"completed","conclusion":"success","number":1,"started_at":"2021-12-16T14:51:34.000Z","completed_at":"2021-12-16T14:51:37.000Z"},{"name":"Run actions/checkout@v2","status":"completed","conclusion":"success","number":2,"started_at":"2021-12-16T14:51:37.000Z","completed_at":"2021-12-16T14:51:43.000Z"},{"name":"Set up JDK 1.8","status":"completed","conclusion":"success","number":3,"started_at":"2021-12-16T14:51:43.000Z","completed_at":"2021-12-16T14:51:47.000Z"},{"name":"Run actions/cache@v1","status":"completed","conclusion":"success","number":4,"started_at":"2021-12-16T14:51:47.000Z","completed_at":"2021-12-16T14:51:48.000Z"},{"name":"Test core","status":"completed","conclusion":"failure","number":5,"started_at":"2021-12-16T14:51:48.000Z","completed_at":"2021-12-16T14:59:31.000Z"},{"name":"Test dhis-web","status":"completed","conclusion":"skipped","number":6,"started_at":"2021-12-16T14:59:31.000Z","completed_at":"2021-12-16T14:59:31.000Z"},{"name":"Post Run actions/cache@v1","status":"completed","conclusion":"skipped","number":10,"started_at":"2021-12-16T14:59:31.000Z","completed_at":"2021-12-16T14:59:31.000Z"},{"name":"Post Set up JDK 1.8","status":"completed","conclusion":"success","number":11,"started_at":"2021-12-16T14:59:31.000Z","completed_at":"2021-12-16T14:59:31.000Z"},{"name":"Post Run actions/checkout@v2","status":"completed","conclusion":"success","number":12,"started_at":"2021-12-16T14:59:31.000Z","completed_at":"2021-12-16T14:59:31.000Z"},{"name":"Complete job","status":"completed","conclusion":"success","number":13,"started_at":"2021-12-16T14:59:31.000Z","completed_at":"2021-12-16T14:59:32.000Z"}],"check_run_url":"https://api.github.com/repos/dhis2/dhis2-core/check-runs/4549025826","labels":["ubuntu-latest"],"runner_id":6,"runner_name":"GitHub Actions 6","runner_group_id":2,"runner_group_name":"GitHub Actions"}]}