{"total_count":4,"jobs":[{"id":56481866197,"run_id":19714091102,"workflow_name":"Test","head_branch":"DHIS2-19185_2.40","run_url":"https://api.github.com/repos/dhis2/dhis2-core/actions/runs/19714091102","run_attempt":1,"node_id":"CR_kwDOA_1uaM8AAAANJpTh1Q","head_sha":"b3f04ae25d581867be791167d5e9b9373d309751","url":"https://api.github.com/repos/dhis2/dhis2-core/actions/jobs/56481866197","html_url":"https://github.com/dhis2/dhis2-core/actions/runs/19714091102/job/56481866197","status":"completed","conclusion":"failure","created_at":"2025-11-26T18:40:37Z","started_at":"2025-11-26T18:40:39Z","completed_at":"2025-11-26T18:42:17Z","name":"integration-test","steps":[{"name":"Set up job","status":"completed","conclusion":"success","number":1,"started_at":"2025-11-26T18:40:39Z","completed_at":"2025-11-26T18:40:42Z"},{"name":"Run actions/checkout@v6","status":"completed","conclusion":"success","number":2,"started_at":"2025-11-26T18:40:42Z","completed_at":"2025-11-26T18:40:46Z"},{"name":"Set up JDK 11","status":"completed","conclusion":"success","number":3,"started_at":"2025-11-26T18:40:46Z","completed_at":"2025-11-26T18:40:52Z"},{"name":"Run integration tests","status":"completed","conclusion":"failure","number":4,"started_at":"2025-11-26T18:40:52Z","completed_at":"2025-11-26T18:42:14Z"},{"name":"Upload test logs on failure","status":"completed","conclusion":"failure","number":5,"started_at":"2025-11-26T18:42:14Z","completed_at":"2025-11-26T18:42:15Z"},{"name":"Report coverage to codecov","status":"completed","conclusion":"skipped","number":6,"started_at":"2025-11-26T18:42:15Z","completed_at":"2025-11-26T18:42:15Z"},{"name":"Tar jacoco coverage report to debug","status":"completed","conclusion":"skipped","number":7,"started_at":"2025-11-26T18:42:15Z","completed_at":"2025-11-26T18:42:15Z"},{"name":"Upload jacoco coverage report to debug","status":"completed","conclusion":"skipped","number":8,"started_at":"2025-11-26T18:42:15Z","completed_at":"2025-11-26T18:42:15Z"},{"name":"Generate surefire aggregate report","status":"completed","conclusion":"skipped","number":9,"started_at":"2025-11-26T18:42:15Z","completed_at":"2025-11-26T18:42:15Z"},{"name":"Tar surefire individual reports","status":"completed","conclusion":"skipped","number":10,"started_at":"2025-11-26T18:42:15Z","completed_at":"2025-11-26T18:42:15Z"},{"name":"Archive surefire reports","status":"completed","conclusion":"skipped","number":11,"started_at":"2025-11-26T18:42:15Z","completed_at":"2025-11-26T18:42:15Z"},{"name":"Post Set up JDK 11","status":"completed","conclusion":"success","number":21,"started_at":"2025-11-26T18:42:15Z","completed_at":"2025-11-26T18:42:15Z"},{"name":"Post Run actions/checkout@v6","status":"completed","conclusion":"success","number":22,"started_at":"2025-11-26T18:42:15Z","completed_at":"2025-11-26T18:42:16Z"},{"name":"Complete job","status":"completed","conclusion":"success","number":23,"started_at":"2025-11-26T18:42:16Z","completed_at":"2025-11-26T18:42:16Z"}],"check_run_url":"https://api.github.com/repos/dhis2/dhis2-core/check-runs/56481866197","labels":["ubuntu-latest"],"runner_id":1000132059,"runner_name":"GitHub Actions 1000132059","runner_group_id":0,"runner_group_name":"GitHub Actions"},{"id":56481866204,"run_id":19714091102,"workflow_name":"Test","head_branch":"DHIS2-19185_2.40","run_url":"https://api.github.com/repos/dhis2/dhis2-core/actions/runs/19714091102","run_attempt":1,"node_id":"CR_kwDOA_1uaM8AAAANJpTh3A","head_sha":"b3f04ae25d581867be791167d5e9b9373d309751","url":"https://api.github.com/repos/dhis2/dhis2-core/actions/jobs/56481866204","html_url":"https://github.com/dhis2/dhis2-core/actions/runs/19714091102/job/56481866204","status":"completed","conclusion":"failure","created_at":"2025-11-26T18:40:37Z","started_at":"2025-11-26T18:40:39Z","completed_at":"2025-11-26T18:42:12Z","name":"integration-h2-test","steps":[{"name":"Set up job","status":"completed","conclusion":"success","number":1,"started_at":"2025-11-26T18:40:39Z","completed_at":"2025-11-26T18:40:41Z"},{"name":"Run actions/checkout@v6","status":"completed","conclusion":"success","number":2,"started_at":"2025-11-26T18:40:41Z","completed_at":"2025-11-26T18:40:44Z"},{"name":"Set up JDK 11","status":"completed","conclusion":"success","number":3,"started_at":"2025-11-26T18:40:44Z","completed_at":"2025-11-26T18:40:49Z"},{"name":"Run integration h2 tests","status":"completed","conclusion":"failure","number":4,"started_at":"2025-11-26T18:40:49Z","completed_at":"2025-11-26T18:42:09Z"},{"name":"Upload test logs on failure","status":"completed","conclusion":"failure","number":5,"started_at":"2025-11-26T18:42:09Z","completed_at":"2025-11-26T18:42:10Z"},{"name":"Report coverage to codecov","status":"completed","conclusion":"skipped","number":6,"started_at":"2025-11-26T18:42:10Z","completed_at":"2025-11-26T18:42:10Z"},{"name":"Tar jacoco coverage report to debug","status":"completed","conclusion":"skipped","number":7,"started_at":"2025-11-26T18:42:10Z","completed_at":"2025-11-26T18:42:10Z"},{"name":"Upload jacoco coverage report to debug","status":"completed","conclusion":"skipped","number":8,"started_at":"2025-11-26T18:42:10Z","completed_at":"2025-11-26T18:42:10Z"},{"name":"Generate surefire aggregate report","status":"completed","conclusion":"skipped","number":9,"started_at":"2025-11-26T18:42:10Z","completed_at":"2025-11-26T18:42:10Z"},{"name":"Tar surefire individual reports","status":"completed","conclusion":"skipped","number":10,"started_at":"2025-11-26T18:42:10Z","completed_at":"2025-11-26T18:42:10Z"},{"name":"Archive surefire reports","status":"completed","conclusion":"skipped","number":11,"started_at":"2025-11-26T18:42:10Z","completed_at":"2025-11-26T18:42:10Z"},{"name":"Post Set up JDK 11","status":"completed","conclusion":"success","number":21,"started_at":"2025-11-26T18:42:10Z","completed_at":"2025-11-26T18:42:11Z"},{"name":"Post Run actions/checkout@v6","status":"completed","conclusion":"success","number":22,"started_at":"2025-11-26T18:42:11Z","completed_at":"2025-11-26T18:42:11Z"},{"name":"Complete job","status":"completed","conclusion":"success","number":23,"started_at":"2025-11-26T18:42:11Z","completed_at":"2025-11-26T18:42:11Z"}],"check_run_url":"https://api.github.com/repos/dhis2/dhis2-core/check-runs/56481866204","labels":["ubuntu-latest"],"runner_id":1000132060,"runner_name":"GitHub Actions 1000132060","runner_group_id":0,"runner_group_name":"GitHub Actions"},{"id":56481866213,"run_id":19714091102,"workflow_name":"Test","head_branch":"DHIS2-19185_2.40","run_url":"https://api.github.com/repos/dhis2/dhis2-core/actions/runs/19714091102","run_attempt":1,"node_id":"CR_kwDOA_1uaM8AAAANJpTh5Q","head_sha":"b3f04ae25d581867be791167d5e9b9373d309751","url":"https://api.github.com/repos/dhis2/dhis2-core/actions/jobs/56481866213","html_url":"https://github.com/dhis2/dhis2-core/actions/runs/19714091102/job/56481866213","status":"completed","conclusion":"failure","created_at":"2025-11-26T18:40:37Z","started_at":"2025-11-26T18:40:39Z","completed_at":"2025-11-26T18:43:46Z","name":"unit-test","steps":[{"name":"Set up job","status":"completed","conclusion":"success","number":1,"started_at":"2025-11-26T18:40:39Z","completed_at":"2025-11-26T18:40:41Z"},{"name":"Run actions/checkout@v6","status":"completed","conclusion":"success","number":2,"started_at":"2025-11-26T18:40:41Z","completed_at":"2025-11-26T18:40:44Z"},{"name":"Set up JDK 11","status":"completed","conclusion":"success","number":3,"started_at":"2025-11-26T18:40:44Z","completed_at":"2025-11-26T18:40:49Z"},{"name":"Run unit tests","status":"completed","conclusion":"failure","number":4,"started_at":"2025-11-26T18:40:49Z","completed_at":"2025-11-26T18:43:44Z"},{"name":"Report coverage to codecov","status":"completed","conclusion":"skipped","number":5,"started_at":"2025-11-26T18:43:44Z","completed_at":"2025-11-26T18:43:44Z"},{"name":"Tar jacoco coverage report to debug","status":"completed","conclusion":"skipped","number":6,"started_at":"2025-11-26T18:43:44Z","completed_at":"2025-11-26T18:43:44Z"},{"name":"Upload jacoco coverage report to debug","status":"completed","conclusion":"skipped","number":7,"started_at":"2025-11-26T18:43:44Z","completed_at":"2025-11-26T18:43:44Z"},{"name":"Test dhis-web","status":"completed","conclusion":"skipped","number":8,"started_at":"2025-11-26T18:43:44Z","completed_at":"2025-11-26T18:43:44Z"},{"name":"Generate surefire aggregate report","status":"completed","conclusion":"skipped","number":9,"started_at":"2025-11-26T18:43:44Z","completed_at":"2025-11-26T18:43:44Z"},{"name":"Tar surefire individual reports","status":"completed","conclusion":"skipped","number":10,"started_at":"2025-11-26T18:43:44Z","completed_at":"2025-11-26T18:43:44Z"},{"name":"Archive surefire reports","status":"completed","conclusion":"skipped","number":11,"started_at":"2025-11-26T18:43:44Z","completed_at":"2025-11-26T18:43:44Z"},{"name":"Post Set up JDK 11","status":"completed","conclusion":"success","number":21,"started_at":"2025-11-26T18:43:44Z","completed_at":"2025-11-26T18:43:44Z"},{"name":"Post Run actions/checkout@v6","status":"completed","conclusion":"success","number":22,"started_at":"2025-11-26T18:43:44Z","completed_at":"2025-11-26T18:43:44Z"},{"name":"Complete job","status":"completed","conclusion":"success","number":23,"started_at":"2025-11-26T18:43:44Z","completed_at":"2025-11-26T18:43:44Z"}],"check_run_url":"https://api.github.com/repos/dhis2/dhis2-core/check-runs/56481866213","labels":["ubuntu-latest"],"runner_id":1000132058,"runner_name":"GitHub Actions 1000132058","runner_group_id":0,"runner_group_name":"GitHub Actions"},{"id":56482106697,"run_id":19714091102,"workflow_name":"Test","head_branch":"DHIS2-19185_2.40","run_url":"https://api.github.com/repos/dhis2/dhis2-core/actions/runs/19714091102","run_attempt":1,"node_id":"CR_kwDOA_1uaM8AAAANJpiNSQ","head_sha":"b3f04ae25d581867be791167d5e9b9373d309751","url":"https://api.github.com/repos/dhis2/dhis2-core/actions/jobs/56482106697","html_url":"https://github.com/dhis2/dhis2-core/actions/runs/19714091102/job/56482106697","status":"completed","conclusion":"skipped","created_at":"2025-11-26T18:43:46Z","started_at":"2025-11-26T18:43:46Z","completed_at":"2025-11-26T18:43:46Z","name":"send-slack-message","steps":[],"check_run_url":"https://api.github.com/repos/dhis2/dhis2-core/check-runs/56482106697","labels":["ubuntu-latest"],"runner_id":null,"runner_name":null,"runner_group_id":null,"runner_group_name":null}]}