{"total_count":4,"jobs":[{"id":19085300861,"run_id":7015640235,"workflow_name":"Test","head_branch":"remove-HibernateConfigurationProvider","run_url":"https://api.github.com/repos/dhis2/dhis2-core/actions/runs/7015640235","run_attempt":1,"node_id":"CR_kwDOA_1uaM8AAAAEcZKUfQ","head_sha":"6850bbadba256d8a0d92f0f5361ce52b19f27fcc","url":"https://api.github.com/repos/dhis2/dhis2-core/actions/jobs/19085300861","html_url":"https://github.com/dhis2/dhis2-core/actions/runs/7015640235/job/19085300861","status":"completed","conclusion":"failure","created_at":"2023-11-28T07:42:26Z","started_at":"2023-11-28T07:42:33Z","completed_at":"2023-11-28T07:44:57Z","name":"unit-test","steps":[{"name":"Set up job","status":"completed","conclusion":"success","number":1,"started_at":"2023-11-28T07:42:33.000Z","completed_at":"2023-11-28T07:42:35.000Z"},{"name":"Run actions/checkout@v4","status":"completed","conclusion":"success","number":2,"started_at":"2023-11-28T07:42:35.000Z","completed_at":"2023-11-28T07:42:39.000Z"},{"name":"Set up JDK 17","status":"completed","conclusion":"success","number":3,"started_at":"2023-11-28T07:42:39.000Z","completed_at":"2023-11-28T07:42:40.000Z"},{"name":"Test core","status":"completed","conclusion":"failure","number":4,"started_at":"2023-11-28T07:42:41.000Z","completed_at":"2023-11-28T07:44:52.000Z"},{"name":"Report coverage to codecov","status":"completed","conclusion":"skipped","number":5,"started_at":"2023-11-28T07:44:52.000Z","completed_at":"2023-11-28T07:44:52.000Z"},{"name":"Tar jacoco coverage report to debug","status":"completed","conclusion":"skipped","number":6,"started_at":"2023-11-28T07:44:52.000Z","completed_at":"2023-11-28T07:44:52.000Z"},{"name":"Upload jacoco coverage report to debug","status":"completed","conclusion":"skipped","number":7,"started_at":"2023-11-28T07:44:52.000Z","completed_at":"2023-11-28T07:44:52.000Z"},{"name":"Test dhis-web","status":"completed","conclusion":"skipped","number":8,"started_at":"2023-11-28T07:44:52.000Z","completed_at":"2023-11-28T07:44:52.000Z"},{"name":"Generate surefire aggregate report","status":"completed","conclusion":"skipped","number":9,"started_at":"2023-11-28T07:44:52.000Z","completed_at":"2023-11-28T07:44:52.000Z"},{"name":"Tar surefire individual reports","status":"completed","conclusion":"skipped","number":10,"started_at":"2023-11-28T07:44:52.000Z","completed_at":"2023-11-28T07:44:52.000Z"},{"name":"Archive surefire reports","status":"completed","conclusion":"skipped","number":11,"started_at":"2023-11-28T07:44:52.000Z","completed_at":"2023-11-28T07:44:52.000Z"},{"name":"Post Set up JDK 17","status":"completed","conclusion":"success","number":21,"started_at":"2023-11-28T07:44:52.000Z","completed_at":"2023-11-28T07:44:52.000Z"},{"name":"Post Run actions/checkout@v4","status":"completed","conclusion":"success","number":22,"started_at":"2023-11-28T07:44:52.000Z","completed_at":"2023-11-28T07:44:52.000Z"},{"name":"Complete job","status":"completed","conclusion":"success","number":23,"started_at":"2023-11-28T07:44:52.000Z","completed_at":"2023-11-28T07:44:52.000Z"}],"check_run_url":"https://api.github.com/repos/dhis2/dhis2-core/check-runs/19085300861","labels":["ubuntu-latest"],"runner_id":14,"runner_name":"GitHub Actions 14","runner_group_id":2,"runner_group_name":"GitHub Actions"},{"id":19085301094,"run_id":7015640235,"workflow_name":"Test","head_branch":"remove-HibernateConfigurationProvider","run_url":"https://api.github.com/repos/dhis2/dhis2-core/actions/runs/7015640235","run_attempt":1,"node_id":"CR_kwDOA_1uaM8AAAAEcZKVZg","head_sha":"6850bbadba256d8a0d92f0f5361ce52b19f27fcc","url":"https://api.github.com/repos/dhis2/dhis2-core/actions/jobs/19085301094","html_url":"https://github.com/dhis2/dhis2-core/actions/runs/7015640235/job/19085301094","status":"completed","conclusion":"failure","created_at":"2023-11-28T07:42:27Z","started_at":"2023-11-28T07:42:32Z","completed_at":"2023-11-28T07:44:57Z","name":"integration-test","steps":[{"name":"Set up job","status":"completed","conclusion":"success","number":1,"started_at":"2023-11-28T07:42:32.000Z","completed_at":"2023-11-28T07:42:33.000Z"},{"name":"Run actions/checkout@v4","status":"completed","conclusion":"success","number":2,"started_at":"2023-11-28T07:42:33.000Z","completed_at":"2023-11-28T07:42:37.000Z"},{"name":"Set up JDK 17","status":"completed","conclusion":"success","number":3,"started_at":"2023-11-28T07:42:38.000Z","completed_at":"2023-11-28T07:42:39.000Z"},{"name":"Run integration tests","status":"completed","conclusion":"failure","number":4,"started_at":"2023-11-28T07:42:39.000Z","completed_at":"2023-11-28T07:44:54.000Z"},{"name":"Upload test logs on failure","status":"completed","conclusion":"failure","number":5,"started_at":"2023-11-28T07:44:54.000Z","completed_at":"2023-11-28T07:44:55.000Z"},{"name":"Report coverage to codecov","status":"completed","conclusion":"skipped","number":6,"started_at":"2023-11-28T07:44:56.000Z","completed_at":"2023-11-28T07:44:56.000Z"},{"name":"Tar jacoco coverage report to debug","status":"completed","conclusion":"skipped","number":7,"started_at":"2023-11-28T07:44:56.000Z","completed_at":"2023-11-28T07:44:56.000Z"},{"name":"Upload jacoco coverage report to debug","status":"completed","conclusion":"skipped","number":8,"started_at":"2023-11-28T07:44:56.000Z","completed_at":"2023-11-28T07:44:56.000Z"},{"name":"Generate surefire aggregate report","status":"completed","conclusion":"skipped","number":9,"started_at":"2023-11-28T07:44:56.000Z","completed_at":"2023-11-28T07:44:56.000Z"},{"name":"Tar surefire individual reports","status":"completed","conclusion":"skipped","number":10,"started_at":"2023-11-28T07:44:56.000Z","completed_at":"2023-11-28T07:44:56.000Z"},{"name":"Archive surefire reports","status":"completed","conclusion":"skipped","number":11,"started_at":"2023-11-28T07:44:56.000Z","completed_at":"2023-11-28T07:44:56.000Z"},{"name":"Post Set up JDK 17","status":"completed","conclusion":"success","number":21,"started_at":"2023-11-28T07:44:56.000Z","completed_at":"2023-11-28T07:44:56.000Z"},{"name":"Post Run actions/checkout@v4","status":"completed","conclusion":"success","number":22,"started_at":"2023-11-28T07:44:56.000Z","completed_at":"2023-11-28T07:44:56.000Z"},{"name":"Complete job","status":"completed","conclusion":"success","number":23,"started_at":"2023-11-28T07:44:56.000Z","completed_at":"2023-11-28T07:44:56.000Z"}],"check_run_url":"https://api.github.com/repos/dhis2/dhis2-core/check-runs/19085301094","labels":["ubuntu-latest"],"runner_id":15,"runner_name":"GitHub Actions 15","runner_group_id":2,"runner_group_name":"GitHub Actions"},{"id":19085301225,"run_id":7015640235,"workflow_name":"Test","head_branch":"remove-HibernateConfigurationProvider","run_url":"https://api.github.com/repos/dhis2/dhis2-core/actions/runs/7015640235","run_attempt":1,"node_id":"CR_kwDOA_1uaM8AAAAEcZKV6Q","head_sha":"6850bbadba256d8a0d92f0f5361ce52b19f27fcc","url":"https://api.github.com/repos/dhis2/dhis2-core/actions/jobs/19085301225","html_url":"https://github.com/dhis2/dhis2-core/actions/runs/7015640235/job/19085301225","status":"completed","conclusion":"failure","created_at":"2023-11-28T07:42:27Z","started_at":"2023-11-28T07:42:32Z","completed_at":"2023-11-28T07:44:39Z","name":"integration-h2-test","steps":[{"name":"Set up job","status":"completed","conclusion":"success","number":1,"started_at":"2023-11-28T07:42:31.000Z","completed_at":"2023-11-28T07:42:33.000Z"},{"name":"Run actions/checkout@v4","status":"completed","conclusion":"success","number":2,"started_at":"2023-11-28T07:42:33.000Z","completed_at":"2023-11-28T07:42:37.000Z"},{"name":"Set up JDK 17","status":"completed","conclusion":"success","number":3,"started_at":"2023-11-28T07:42:37.000Z","completed_at":"2023-11-28T07:42:38.000Z"},{"name":"Run integration h2 tests","status":"completed","conclusion":"failure","number":4,"started_at":"2023-11-28T07:42:38.000Z","completed_at":"2023-11-28T07:44:36.000Z"},{"name":"Upload test logs on failure","status":"completed","conclusion":"failure","number":5,"started_at":"2023-11-28T07:44:36.000Z","completed_at":"2023-11-28T07:44:37.000Z"},{"name":"Report coverage to codecov","status":"completed","conclusion":"skipped","number":6,"started_at":"2023-11-28T07:44:37.000Z","completed_at":"2023-11-28T07:44:37.000Z"},{"name":"Tar jacoco coverage report to debug","status":"completed","conclusion":"skipped","number":7,"started_at":"2023-11-28T07:44:37.000Z","completed_at":"2023-11-28T07:44:37.000Z"},{"name":"Upload jacoco coverage report to debug","status":"completed","conclusion":"skipped","number":8,"started_at":"2023-11-28T07:44:37.000Z","completed_at":"2023-11-28T07:44:37.000Z"},{"name":"Generate surefire aggregate report","status":"completed","conclusion":"skipped","number":9,"started_at":"2023-11-28T07:44:37.000Z","completed_at":"2023-11-28T07:44:37.000Z"},{"name":"Tar surefire individual reports","status":"completed","conclusion":"skipped","number":10,"started_at":"2023-11-28T07:44:37.000Z","completed_at":"2023-11-28T07:44:37.000Z"},{"name":"Archive surefire reports","status":"completed","conclusion":"skipped","number":11,"started_at":"2023-11-28T07:44:37.000Z","completed_at":"2023-11-28T07:44:37.000Z"},{"name":"Post Set up JDK 17","status":"completed","conclusion":"success","number":21,"started_at":"2023-11-28T07:44:37.000Z","completed_at":"2023-11-28T07:44:37.000Z"},{"name":"Post Run actions/checkout@v4","status":"completed","conclusion":"success","number":22,"started_at":"2023-11-28T07:44:37.000Z","completed_at":"2023-11-28T07:44:37.000Z"},{"name":"Complete job","status":"completed","conclusion":"success","number":23,"started_at":"2023-11-28T07:44:37.000Z","completed_at":"2023-11-28T07:44:37.000Z"}],"check_run_url":"https://api.github.com/repos/dhis2/dhis2-core/check-runs/19085301225","labels":["ubuntu-latest"],"runner_id":16,"runner_name":"GitHub Actions 16","runner_group_id":2,"runner_group_name":"GitHub Actions"},{"id":19085356941,"run_id":7015640235,"workflow_name":"Test","head_branch":"remove-HibernateConfigurationProvider","run_url":"https://api.github.com/repos/dhis2/dhis2-core/actions/runs/7015640235","run_attempt":1,"node_id":"CR_kwDOA_1uaM8AAAAEcZNvjQ","head_sha":"6850bbadba256d8a0d92f0f5361ce52b19f27fcc","url":"https://api.github.com/repos/dhis2/dhis2-core/actions/jobs/19085356941","html_url":"https://github.com/dhis2/dhis2-core/actions/runs/7015640235/job/19085356941","status":"completed","conclusion":"skipped","created_at":"2023-11-28T07:44:58Z","started_at":"2023-11-28T07:44:58Z","completed_at":"2023-11-28T07:44:58Z","name":"send-slack-message","steps":[],"check_run_url":"https://api.github.com/repos/dhis2/dhis2-core/check-runs/19085356941","labels":[],"runner_id":null,"runner_name":null,"runner_group_id":null,"runner_group_name":null}]}