{"total_count":4,"jobs":[{"id":25056118660,"run_id":9113772436,"workflow_name":"Test","head_branch":"DHIS2-17292","run_url":"https://api.github.com/repos/dhis2/dhis2-core/actions/runs/9113772436","run_attempt":1,"node_id":"CR_kwDOA_1uaM8AAAAF1XYHhA","head_sha":"1f24a4c274e2c597959d4bd5c8956f08498e31dc","url":"https://api.github.com/repos/dhis2/dhis2-core/actions/jobs/25056118660","html_url":"https://github.com/dhis2/dhis2-core/actions/runs/9113772436/job/25056118660","status":"completed","conclusion":"success","created_at":"2024-05-16T14:06:08Z","started_at":"2024-05-16T14:06:27Z","completed_at":"2024-05-16T14:15:38Z","name":"integration-h2-test","steps":[{"name":"Set up job","status":"completed","conclusion":"success","number":1,"started_at":"2024-05-16T14:06:25Z","completed_at":"2024-05-16T14:06:29Z"},{"name":"Run actions/checkout@v4","status":"completed","conclusion":"success","number":2,"started_at":"2024-05-16T14:06:29Z","completed_at":"2024-05-16T14:06:35Z"},{"name":"Set up JDK 17","status":"completed","conclusion":"success","number":3,"started_at":"2024-05-16T14:06:37Z","completed_at":"2024-05-16T14:06:40Z"},{"name":"Run integration h2 tests","status":"completed","conclusion":"success","number":4,"started_at":"2024-05-16T14:06:41Z","completed_at":"2024-05-16T14:15:25Z"},{"name":"Upload test logs on failure","status":"completed","conclusion":"skipped","number":5,"started_at":"2024-05-16T14:15:26Z","completed_at":"2024-05-16T14:15:26Z"},{"name":"Report coverage to codecov","status":"completed","conclusion":"success","number":6,"started_at":"2024-05-16T14:15:26Z","completed_at":"2024-05-16T14:15:30Z"},{"name":"Tar jacoco coverage report to debug","status":"completed","conclusion":"success","number":7,"started_at":"2024-05-16T14:15:30Z","completed_at":"2024-05-16T14:15:30Z"},{"name":"Upload jacoco coverage report to debug","status":"completed","conclusion":"success","number":8,"started_at":"2024-05-16T14:15:31Z","completed_at":"2024-05-16T14:15:32Z"},{"name":"Generate surefire aggregate report","status":"completed","conclusion":"success","number":9,"started_at":"2024-05-16T14:15:33Z","completed_at":"2024-05-16T14:15:35Z"},{"name":"Tar surefire individual reports","status":"completed","conclusion":"success","number":10,"started_at":"2024-05-16T14:15:35Z","completed_at":"2024-05-16T14:15:35Z"},{"name":"Archive surefire reports","status":"completed","conclusion":"success","number":11,"started_at":"2024-05-16T14:15:35Z","completed_at":"2024-05-16T14:15:36Z"},{"name":"Post Set up JDK 17","status":"completed","conclusion":"success","number":21,"started_at":"2024-05-16T14:15:36Z","completed_at":"2024-05-16T14:15:36Z"},{"name":"Post Run actions/checkout@v4","status":"completed","conclusion":"success","number":22,"started_at":"2024-05-16T14:15:36Z","completed_at":"2024-05-16T14:15:37Z"},{"name":"Complete job","status":"completed","conclusion":"success","number":23,"started_at":"2024-05-16T14:15:37Z","completed_at":"2024-05-16T14:15:37Z"}],"check_run_url":"https://api.github.com/repos/dhis2/dhis2-core/check-runs/25056118660","labels":["ubuntu-latest"],"runner_id":20,"runner_name":"GitHub Actions 20","runner_group_id":2,"runner_group_name":"GitHub Actions"},{"id":25056118962,"run_id":9113772436,"workflow_name":"Test","head_branch":"DHIS2-17292","run_url":"https://api.github.com/repos/dhis2/dhis2-core/actions/runs/9113772436","run_attempt":1,"node_id":"CR_kwDOA_1uaM8AAAAF1XYIsg","head_sha":"1f24a4c274e2c597959d4bd5c8956f08498e31dc","url":"https://api.github.com/repos/dhis2/dhis2-core/actions/jobs/25056118962","html_url":"https://github.com/dhis2/dhis2-core/actions/runs/9113772436/job/25056118962","status":"completed","conclusion":"success","created_at":"2024-05-16T14:06:08Z","started_at":"2024-05-16T14:06:18Z","completed_at":"2024-05-16T14:20:09Z","name":"integration-test","steps":[{"name":"Set up job","status":"completed","conclusion":"success","number":1,"started_at":"2024-05-16T14:06:18Z","completed_at":"2024-05-16T14:06:19Z"},{"name":"Run actions/checkout@v4","status":"completed","conclusion":"success","number":2,"started_at":"2024-05-16T14:06:19Z","completed_at":"2024-05-16T14:06:22Z"},{"name":"Set up JDK 17","status":"completed","conclusion":"success","number":3,"started_at":"2024-05-16T14:06:23Z","completed_at":"2024-05-16T14:06:28Z"},{"name":"Run integration tests","status":"completed","conclusion":"success","number":4,"started_at":"2024-05-16T14:06:28Z","completed_at":"2024-05-16T14:19:56Z"},{"name":"Upload test logs on failure","status":"completed","conclusion":"skipped","number":5,"started_at":"2024-05-16T14:19:57Z","completed_at":"2024-05-16T14:19:57Z"},{"name":"Report coverage to codecov","status":"completed","conclusion":"success","number":6,"started_at":"2024-05-16T14:19:57Z","completed_at":"2024-05-16T14:19:59Z"},{"name":"Tar jacoco coverage report to debug","status":"completed","conclusion":"success","number":7,"started_at":"2024-05-16T14:19:59Z","completed_at":"2024-05-16T14:20:00Z"},{"name":"Upload jacoco coverage report to debug","status":"completed","conclusion":"success","number":8,"started_at":"2024-05-16T14:20:00Z","completed_at":"2024-05-16T14:20:02Z"},{"name":"Generate surefire aggregate report","status":"completed","conclusion":"success","number":9,"started_at":"2024-05-16T14:20:02Z","completed_at":"2024-05-16T14:20:05Z"},{"name":"Tar surefire individual reports","status":"completed","conclusion":"success","number":10,"started_at":"2024-05-16T14:20:05Z","completed_at":"2024-05-16T14:20:05Z"},{"name":"Archive surefire reports","status":"completed","conclusion":"success","number":11,"started_at":"2024-05-16T14:20:05Z","completed_at":"2024-05-16T14:20:07Z"},{"name":"Post Set up JDK 17","status":"completed","conclusion":"success","number":21,"started_at":"2024-05-16T14:20:07Z","completed_at":"2024-05-16T14:20:07Z"},{"name":"Post Run actions/checkout@v4","status":"completed","conclusion":"success","number":22,"started_at":"2024-05-16T14:20:09Z","completed_at":"2024-05-16T14:20:09Z"},{"name":"Complete job","status":"completed","conclusion":"success","number":23,"started_at":"2024-05-16T14:20:07Z","completed_at":"2024-05-16T14:20:07Z"}],"check_run_url":"https://api.github.com/repos/dhis2/dhis2-core/check-runs/25056118962","labels":["ubuntu-latest"],"runner_id":10,"runner_name":"GitHub Actions 10","runner_group_id":2,"runner_group_name":"GitHub Actions"},{"id":25056119324,"run_id":9113772436,"workflow_name":"Test","head_branch":"DHIS2-17292","run_url":"https://api.github.com/repos/dhis2/dhis2-core/actions/runs/9113772436","run_attempt":1,"node_id":"CR_kwDOA_1uaM8AAAAF1XYKHA","head_sha":"1f24a4c274e2c597959d4bd5c8956f08498e31dc","url":"https://api.github.com/repos/dhis2/dhis2-core/actions/jobs/25056119324","html_url":"https://github.com/dhis2/dhis2-core/actions/runs/9113772436/job/25056119324","status":"completed","conclusion":"success","created_at":"2024-05-16T14:06:08Z","started_at":"2024-05-16T14:06:21Z","completed_at":"2024-05-16T14:12:43Z","name":"unit-test","steps":[{"name":"Set up job","status":"completed","conclusion":"success","number":1,"started_at":"2024-05-16T14:06:21Z","completed_at":"2024-05-16T14:06:22Z"},{"name":"Run actions/checkout@v4","status":"completed","conclusion":"success","number":2,"started_at":"2024-05-16T14:06:22Z","completed_at":"2024-05-16T14:06:26Z"},{"name":"Set up JDK 17","status":"completed","conclusion":"success","number":3,"started_at":"2024-05-16T14:06:26Z","completed_at":"2024-05-16T14:06:32Z"},{"name":"Test core","status":"completed","conclusion":"success","number":4,"started_at":"2024-05-16T14:06:31Z","completed_at":"2024-05-16T14:12:29Z"},{"name":"Report coverage to codecov","status":"completed","conclusion":"success","number":5,"started_at":"2024-05-16T14:12:29Z","completed_at":"2024-05-16T14:12:31Z"},{"name":"Tar jacoco coverage report to debug","status":"completed","conclusion":"success","number":6,"started_at":"2024-05-16T14:12:32Z","completed_at":"2024-05-16T14:12:32Z"},{"name":"Upload jacoco coverage report to debug","status":"completed","conclusion":"success","number":7,"started_at":"2024-05-16T14:12:32Z","completed_at":"2024-05-16T14:12:35Z"},{"name":"Generate surefire aggregate report","status":"completed","conclusion":"success","number":8,"started_at":"2024-05-16T14:12:35Z","completed_at":"2024-05-16T14:12:38Z"},{"name":"Tar surefire individual reports","status":"completed","conclusion":"success","number":9,"started_at":"2024-05-16T14:12:38Z","completed_at":"2024-05-16T14:12:38Z"},{"name":"Archive surefire reports","status":"completed","conclusion":"success","number":10,"started_at":"2024-05-16T14:12:39Z","completed_at":"2024-05-16T14:12:40Z"},{"name":"Post Set up JDK 17","status":"completed","conclusion":"success","number":19,"started_at":"2024-05-16T14:12:43Z","completed_at":"2024-05-16T14:12:43Z"},{"name":"Post Run actions/checkout@v4","status":"completed","conclusion":"success","number":20,"started_at":"2024-05-16T14:12:43Z","completed_at":"2024-05-16T14:12:43Z"},{"name":"Complete job","status":"completed","conclusion":"success","number":21,"started_at":"2024-05-16T14:12:40Z","completed_at":"2024-05-16T14:12:40Z"}],"check_run_url":"https://api.github.com/repos/dhis2/dhis2-core/check-runs/25056119324","labels":["ubuntu-latest"],"runner_id":14,"runner_name":"GitHub Actions 14","runner_group_id":2,"runner_group_name":"GitHub Actions"},{"id":25056876607,"run_id":9113772436,"workflow_name":"Test","head_branch":"DHIS2-17292","run_url":"https://api.github.com/repos/dhis2/dhis2-core/actions/runs/9113772436","run_attempt":1,"node_id":"CR_kwDOA_1uaM8AAAAF1YGYPw","head_sha":"1f24a4c274e2c597959d4bd5c8956f08498e31dc","url":"https://api.github.com/repos/dhis2/dhis2-core/actions/jobs/25056876607","html_url":"https://github.com/dhis2/dhis2-core/actions/runs/9113772436/job/25056876607","status":"completed","conclusion":"skipped","created_at":"2024-05-16T14:20:09Z","started_at":"2024-05-16T14:20:09Z","completed_at":"2024-05-16T14:20:09Z","name":"send-slack-message","steps":[],"check_run_url":"https://api.github.com/repos/dhis2/dhis2-core/check-runs/25056876607","labels":[],"runner_id":null,"runner_name":null,"runner_group_id":null,"runner_group_name":null}]}