{"total_count":2,"jobs":[{"id":33107245849,"run_id":11882126146,"workflow_name":"Run api tests","head_branch":"DHIS2-18417","run_url":"https://api.github.com/repos/dhis2/dhis2-core/actions/runs/11882126146","run_attempt":1,"node_id":"CR_kwDOA_1uaM8AAAAHtVh7GQ","head_sha":"d78e95df8c69f76b9a035a2724166237578e4359","url":"https://api.github.com/repos/dhis2/dhis2-core/actions/jobs/33107245849","html_url":"https://github.com/dhis2/dhis2-core/actions/runs/11882126146/job/33107245849","status":"completed","conclusion":"cancelled","created_at":"2024-11-17T20:52:14Z","started_at":"2024-11-17T20:52:20Z","completed_at":"2024-11-17T20:58:41Z","name":"api-test","steps":[{"name":"Set up job","status":"completed","conclusion":"success","number":1,"started_at":"2024-11-17T20:52:20Z","completed_at":"2024-11-17T20:52:23Z"},{"name":"Run actions/checkout@v4","status":"completed","conclusion":"success","number":2,"started_at":"2024-11-17T20:52:23Z","completed_at":"2024-11-17T20:52:26Z"},{"name":"Set up JDK 17","status":"completed","conclusion":"success","number":3,"started_at":"2024-11-17T20:52:27Z","completed_at":"2024-11-17T20:52:34Z"},{"name":"Login to Docker Hub","status":"completed","conclusion":"success","number":4,"started_at":"2024-11-17T20:52:34Z","completed_at":"2024-11-17T20:52:35Z"},{"name":"Build container image","status":"completed","conclusion":"success","number":5,"started_at":"2024-11-17T20:52:35Z","completed_at":"2024-11-17T20:54:40Z"},{"name":"Run tests","status":"completed","conclusion":"cancelled","number":6,"started_at":"2024-11-17T20:54:40Z","completed_at":"2024-11-17T20:58:36Z"},{"name":"Upload logs","status":"completed","conclusion":"skipped","number":7,"started_at":"2024-11-17T20:58:37Z","completed_at":"2024-11-17T20:58:37Z"},{"name":"Run actions/upload-artifact@v4","status":"completed","conclusion":"skipped","number":8,"started_at":"2024-11-17T20:58:37Z","completed_at":"2024-11-17T20:58:37Z"},{"name":"Post Login to Docker Hub","status":"completed","conclusion":"success","number":14,"started_at":"2024-11-17T20:58:37Z","completed_at":"2024-11-17T20:58:37Z"},{"name":"Post Set up JDK 17","status":"completed","conclusion":"success","number":15,"started_at":"2024-11-17T20:58:37Z","completed_at":"2024-11-17T20:58:37Z"},{"name":"Post Run actions/checkout@v4","status":"completed","conclusion":"success","number":16,"started_at":"2024-11-17T20:58:37Z","completed_at":"2024-11-17T20:58:37Z"},{"name":"Complete job","status":"completed","conclusion":"success","number":17,"started_at":"2024-11-17T20:58:37Z","completed_at":"2024-11-17T20:58:37Z"}],"check_run_url":"https://api.github.com/repos/dhis2/dhis2-core/check-runs/33107245849","labels":["ubuntu-latest"],"runner_id":137,"runner_name":"GitHub Actions 56","runner_group_id":2,"runner_group_name":"GitHub Actions"},{"id":33107313465,"run_id":11882126146,"workflow_name":"Run api tests","head_branch":"DHIS2-18417","run_url":"https://api.github.com/repos/dhis2/dhis2-core/actions/runs/11882126146","run_attempt":1,"node_id":"CR_kwDOA_1uaM8AAAAHtVmDOQ","head_sha":"d78e95df8c69f76b9a035a2724166237578e4359","url":"https://api.github.com/repos/dhis2/dhis2-core/actions/jobs/33107313465","html_url":"https://github.com/dhis2/dhis2-core/actions/runs/11882126146/job/33107313465","status":"completed","conclusion":"cancelled","created_at":"2024-11-17T20:58:42Z","started_at":"2024-11-17T20:58:42Z","completed_at":"2024-11-17T20:58:42Z","name":"send-slack-message","steps":[],"check_run_url":"https://api.github.com/repos/dhis2/dhis2-core/check-runs/33107313465","labels":[],"runner_id":null,"runner_name":null,"runner_group_id":null,"runner_group_name":null}]}