{"total_count":2,"jobs":[{"id":41343768866,"run_id":14730636976,"workflow_name":"Run api tests","head_branch":"DHIS2-19208","run_url":"https://api.github.com/repos/dhis2/dhis2-core/actions/runs/14730636976","run_attempt":1,"node_id":"CR_kwDOA_1uaM8AAAAJoEfZIg","head_sha":"9eab8e0342b6bf7e7337e90cf54a002493888199","url":"https://api.github.com/repos/dhis2/dhis2-core/actions/jobs/41343768866","html_url":"https://github.com/dhis2/dhis2-core/actions/runs/14730636976/job/41343768866","status":"completed","conclusion":"success","created_at":"2025-04-29T11:57:28Z","started_at":"2025-04-29T11:57:34Z","completed_at":"2025-04-29T12:09:27Z","name":"api-test","steps":[{"name":"Set up job","status":"completed","conclusion":"success","number":1,"started_at":"2025-04-29T11:57:34Z","completed_at":"2025-04-29T11:57:35Z"},{"name":"Run actions/checkout@v4","status":"completed","conclusion":"success","number":2,"started_at":"2025-04-29T11:57:35Z","completed_at":"2025-04-29T11:57:41Z"},{"name":"Set up JDK 17","status":"completed","conclusion":"success","number":3,"started_at":"2025-04-29T11:57:42Z","completed_at":"2025-04-29T11:57:46Z"},{"name":"Login to Docker Hub","status":"completed","conclusion":"success","number":4,"started_at":"2025-04-29T11:57:46Z","completed_at":"2025-04-29T11:57:47Z"},{"name":"Build container image","status":"completed","conclusion":"success","number":5,"started_at":"2025-04-29T11:57:47Z","completed_at":"2025-04-29T11:59:48Z"},{"name":"Run tests","status":"completed","conclusion":"success","number":6,"started_at":"2025-04-29T11:59:49Z","completed_at":"2025-04-29T12:09:23Z"},{"name":"Upload logs","status":"completed","conclusion":"skipped","number":7,"started_at":"2025-04-29T12:09:23Z","completed_at":"2025-04-29T12:09:23Z"},{"name":"Run actions/upload-artifact@v4","status":"completed","conclusion":"skipped","number":8,"started_at":"2025-04-29T12:09:23Z","completed_at":"2025-04-29T12:09:23Z"},{"name":"Post Login to Docker Hub","status":"completed","conclusion":"success","number":14,"started_at":"2025-04-29T12:09:23Z","completed_at":"2025-04-29T12:09:23Z"},{"name":"Post Set up JDK 17","status":"completed","conclusion":"success","number":15,"started_at":"2025-04-29T12:09:23Z","completed_at":"2025-04-29T12:09:23Z"},{"name":"Post Run actions/checkout@v4","status":"completed","conclusion":"success","number":16,"started_at":"2025-04-29T12:09:27Z","completed_at":"2025-04-29T12:09:27Z"},{"name":"Complete job","status":"completed","conclusion":"success","number":17,"started_at":"2025-04-29T12:09:24Z","completed_at":"2025-04-29T12:09:24Z"}],"check_run_url":"https://api.github.com/repos/dhis2/dhis2-core/check-runs/41343768866","labels":["ubuntu-latest"],"runner_id":113,"runner_name":"GitHub Actions 32","runner_group_id":2,"runner_group_name":"GitHub Actions"},{"id":41344524275,"run_id":14730636976,"workflow_name":"Run api tests","head_branch":"DHIS2-19208","run_url":"https://api.github.com/repos/dhis2/dhis2-core/actions/runs/14730636976","run_attempt":1,"node_id":"CR_kwDOA_1uaM8AAAAJoFNf8w","head_sha":"9eab8e0342b6bf7e7337e90cf54a002493888199","url":"https://api.github.com/repos/dhis2/dhis2-core/actions/jobs/41344524275","html_url":"https://github.com/dhis2/dhis2-core/actions/runs/14730636976/job/41344524275","status":"completed","conclusion":"skipped","created_at":"2025-04-29T12:09:27Z","started_at":"2025-04-29T12:09:27Z","completed_at":"2025-04-29T12:09:27Z","name":"send-slack-message","steps":[],"check_run_url":"https://api.github.com/repos/dhis2/dhis2-core/check-runs/41344524275","labels":[],"runner_id":null,"runner_name":null,"runner_group_id":null,"runner_group_name":null}]}