{"total_count":2,"jobs":[{"id":60186601578,"run_id":20945140816,"run_url":"https://api.github.com/repos/dhis2/dhis2-core/actions/runs/20945140816","node_id":"CR_kwDOA_1uaM8AAAAOA2aoag","head_branch":"dependabot-maven-dhis-2-2.42-com.h2database-h2-2.4.240","head_sha":"833d95c7285ddfc8ed16a216773fcca8ee6cd2a9","url":"https://api.github.com/repos/dhis2/dhis2-core/actions/jobs/60186601578","html_url":"https://github.com/dhis2/dhis2-core/actions/runs/20945140816/job/60186601578","status":"completed","conclusion":"success","created_at":"2026-01-13T04:51:56Z","started_at":"2026-01-13T04:51:57Z","completed_at":"2026-01-13T05:06:54Z","name":"api-test","steps":[{"name":"Set up job","status":"completed","conclusion":"success","number":1,"started_at":"2026-01-13T04:51:58Z","completed_at":"2026-01-13T04:52:00Z"},{"name":"Run actions/checkout@v6","status":"completed","conclusion":"success","number":2,"started_at":"2026-01-13T04:52:00Z","completed_at":"2026-01-13T04:52:03Z"},{"name":"Set up JDK 17","status":"completed","conclusion":"success","number":3,"started_at":"2026-01-13T04:52:03Z","completed_at":"2026-01-13T04:52:05Z"},{"name":"Login to Docker Hub","status":"completed","conclusion":"skipped","number":4,"started_at":"2026-01-13T04:52:05Z","completed_at":"2026-01-13T04:52:05Z"},{"name":"Build container image","status":"completed","conclusion":"success","number":5,"started_at":"2026-01-13T04:52:05Z","completed_at":"2026-01-13T04:55:18Z"},{"name":"Run tests","status":"completed","conclusion":"success","number":6,"started_at":"2026-01-13T04:55:18Z","completed_at":"2026-01-13T05:06:50Z"},{"name":"Upload logs","status":"completed","conclusion":"skipped","number":7,"started_at":"2026-01-13T05:06:50Z","completed_at":"2026-01-13T05:06:50Z"},{"name":"Run actions/upload-artifact@v6","status":"completed","conclusion":"skipped","number":8,"started_at":"2026-01-13T05:06:50Z","completed_at":"2026-01-13T05:06:50Z"},{"name":"Post Set up JDK 17","status":"completed","conclusion":"success","number":15,"started_at":"2026-01-13T05:06:50Z","completed_at":"2026-01-13T05:06:52Z"},{"name":"Post Run actions/checkout@v6","status":"completed","conclusion":"success","number":16,"started_at":"2026-01-13T05:06:52Z","completed_at":"2026-01-13T05:06:52Z"},{"name":"Complete job","status":"completed","conclusion":"success","number":17,"started_at":"2026-01-13T05:06:52Z","completed_at":"2026-01-13T05:06:52Z"}],"check_run_url":"https://api.github.com/repos/dhis2/dhis2-core/check-runs/60186601578","labels":["ubuntu-latest"],"runner_id":1000157334,"runner_name":"GitHub Actions 1000157334","runner_group_id":0,"runner_group_name":"GitHub Actions","run_attempt":1,"workflow_name":"Run api tests"},{"id":60187421419,"run_id":20945140816,"run_url":"https://api.github.com/repos/dhis2/dhis2-core/actions/runs/20945140816","node_id":"CR_kwDOA_1uaM8AAAAOA3Mq6w","head_branch":"dependabot-maven-dhis-2-2.42-com.h2database-h2-2.4.240","head_sha":"833d95c7285ddfc8ed16a216773fcca8ee6cd2a9","url":"https://api.github.com/repos/dhis2/dhis2-core/actions/jobs/60187421419","html_url":"https://github.com/dhis2/dhis2-core/actions/runs/20945140816/job/60187421419","status":"completed","conclusion":"skipped","created_at":"2026-01-13T05:06:54Z","started_at":"2026-01-13T05:06:54Z","completed_at":"2026-01-13T05:06:54Z","name":"send-slack-message","check_run_url":"https://api.github.com/repos/dhis2/dhis2-core/check-runs/60187421419","labels":["ubuntu-latest"],"run_attempt":1,"workflow_name":"Run api tests"}]}